yuheng_osmapi/const.py
yuheng_osmapi/core_changeset.py
yuheng_osmapi/core_element.py
yuheng_osmapi/oauth.py
yuheng_osmapi/tools.py
yuheng_osmapi-1.0.1.dist-info/LICENSE
yuheng_osmapi-1.0.1.dist-info/METADATA
yuheng_osmapi-1.0.1.dist-info/WHEEL
yuheng_osmapi-1.0.1.dist-info/RECORD
