Metadata-Version: 2.1
Name: yuheng-osmapi
Version: 1.0.1
Summary: 
License: MIT
Author: 快乐的老鼠宝宝
Author-email: laoshubaby@protonmail.com
Requires-Python: >=3.11,<4.0
Classifier: License :: OSI Approved :: MIT License
Classifier: Programming Language :: Python :: 3
Classifier: Programming Language :: Python :: 3.11
Classifier: Programming Language :: Python :: 3.12
Classifier: Programming Language :: Python :: 3.13
Requires-Dist: requests (>=2.32.3,<3.0.0)
